emilys/__init__.py
emilys/files/__init__.py
emilys/files/emd.py
emilys/files/mtf.py
emilys/files/txt.py
emilys/functions/__init__.py
emilys/functions/distributions.py
emilys/functions/peaks.py
emilys/image/__init__.py
emilys/image/arrayplot.py
emilys/image/binning.py
emilys/image/dpc.py
emilys/image/geometry.py
emilys/image/imagedata.py
emilys/image/kernels.py
emilys/image/manipulations.py
emilys/image/peakfit.py
emilys/image/polar.py
emilys/image/powderdif.py
emilys/image/shift.py
emilys/image/thonrings.py
emilys/numerics/__init__.py
emilys/numerics/cluster.py
emilys/numerics/correlation.py
emilys/numerics/linsearch.py
emilys/numerics/lstsq.py
emilys/numerics/mc.py
emilys/numerics/rngdist.py
emilys/numerics/roots.py
emilys/optics/__init__.py
emilys/optics/aberration.py
emilys/optics/aperture.py
emilys/optics/crystal.py
emilys/optics/detector.py
emilys/optics/econst.py
emilys/optics/focusspread.py
emilys/optics/mtf.py
emilys/optics/phonmu.py
emilys/optics/probe.py
emilys/optics/projection.py
emilys/optics/tp1dho.py
emilys/optics/waki.py
emilys/structure/__init__.py
emilys/structure/atom.py
emilys/structure/atomtype.py
emilys/structure/celio.py
emilys/structure/cifio.py
emilys/structure/msd.py
emilys/structure/supercell.py
emilys/structure/xtlio.py
emilys-0.1.8.dist-info/LICENSE
emilys-0.1.8.dist-info/METADATA
emilys-0.1.8.dist-info/WHEEL
emilys-0.1.8.dist-info/top_level.txt
emilys-0.1.8.dist-info/RECORD
