Metadata-Version: 2.1
Name: emilys
Version: 0.1.8
Summary: Python scripts for Electron Microscopy Image anaLYSis
Home-page: https://github.com/ju-bar/emilys
Author: Juri Barthel
Author-email: juribarthel@gmail.com
Classifier: Development Status :: 3 - Alpha
License-File: LICENSE
Requires-Dist: numpy
Requires-Dist: numba
Requires-Dist: scipy
Requires-Dist: matplotlib
Requires-Dist: json
Requires-Dist: h5py
Requires-Dist: fractions
Requires-Dist: importlib
